mcp/__init__.py
mcp/py.typed
mcp/cli/__init__.py
mcp/cli/claude.py
mcp/cli/cli.py
mcp/client/__init__.py
mcp/client/__main__.py
mcp/client/_memory.py
mcp/client/client.py
mcp/client/session.py
mcp/client/session_group.py
mcp/client/sse.py
mcp/client/stdio.py
mcp/client/streamable_http.py
mcp/client/websocket.py
mcp/client/auth/__init__.py
mcp/client/auth/exceptions.py
mcp/client/auth/oauth2.py
mcp/client/auth/utils.py
mcp/client/auth/extensions/__init__.py
mcp/client/auth/extensions/client_credentials.py
mcp/client/experimental/__init__.py
mcp/client/experimental/task_handlers.py
mcp/client/experimental/tasks.py
mcp/os/__init__.py
mcp/os/posix/__init__.py
mcp/os/posix/utilities.py
mcp/os/win32/__init__.py
mcp/os/win32/utilities.py
mcp/server/__init__.py
mcp/server/__main__.py
mcp/server/elicitation.py
mcp/server/models.py
mcp/server/session.py
mcp/server/sse.py
mcp/server/stdio.py
mcp/server/streamable_http.py
mcp/server/streamable_http_manager.py
mcp/server/transport_security.py
mcp/server/validation.py
mcp/server/websocket.py
mcp/server/auth/__init__.py
mcp/server/auth/errors.py
mcp/server/auth/json_response.py
mcp/server/auth/provider.py
mcp/server/auth/routes.py
mcp/server/auth/settings.py
mcp/server/auth/handlers/__init__.py
mcp/server/auth/handlers/authorize.py
mcp/server/auth/handlers/metadata.py
mcp/server/auth/handlers/register.py
mcp/server/auth/handlers/revoke.py
mcp/server/auth/handlers/token.py
mcp/server/auth/middleware/__init__.py
mcp/server/auth/middleware/auth_context.py
mcp/server/auth/middleware/bearer_auth.py
mcp/server/auth/middleware/client_auth.py
mcp/server/experimental/__init__.py
mcp/server/experimental/request_context.py
mcp/server/experimental/session_features.py
mcp/server/experimental/task_context.py
mcp/server/experimental/task_result_handler.py
mcp/server/experimental/task_support.py
mcp/server/lowlevel/__init__.py
mcp/server/lowlevel/experimental.py
mcp/server/lowlevel/func_inspection.py
mcp/server/lowlevel/helper_types.py
test_package_demo-0.1.0.dist-info/licenses/LICENSE
test_package_demo-0.1.0.dist-info/METADATA
test_package_demo-0.1.0.dist-info/WHEEL
test_package_demo-0.1.0.dist-info/top_level.txt
test_package_demo-0.1.0.dist-info/RECORD
