Metadata-Version: 2.4
Name: test-package-demo
Version: 0.1.0
Summary: A test package for demonstrating Python package publishing
Author-email: Test Author <test@example.com>
License: MIT License
Project-URL: Homepage, https://github.com/example/test-package-demo
Project-URL: Repository, https://github.com/example/test-package-demo
Classifier: Programming Language :: Python :: 3
Classifier: License :: OSI Approved :: MIT License
Classifier: Operating System :: OS Independent
Requires-Python: >=3.8
License-File: LICENSE
Dynamic: license-file
